extract_json_from_string/__init__.py
extract_json_from_string/extract_json_from_string.py
extract_json_from_string-0.0.1.dist-info/METADATA
extract_json_from_string-0.0.1.dist-info/WHEEL
extract_json_from_string-0.0.1.dist-info/top_level.txt
extract_json_from_string-0.0.1.dist-info/RECORD
